{
    "0": {
        "address": "952 Sutter St. | 952 Sutter St, San Francisco, CA",
        "price": 2600,
        "link": "https://www.zillow.com//b/952-sutter-st.-san-francisco-ca-5XjxLz/"
    },
    "1": {
        "address": "Parkmerced | 3711 19th Ave, San Francisco, CA",
        "price": 2750,
        "link": "https://www.zillow.com//b/parkmerced-san-francisco-ca-5XjKHx/"
    },
    "3": {
        "address": "950 Franklin, 950 Franklin St APT 25, San Francisco, CA 94109",
        "price": 2695,
        "link": "https://www.zillow.com/https://www.zillow.com/b/950-franklin-san-francisco-ca-5Xj398/"
    },
    "4": {
        "address": "Alta Potrero | 1301 16th St, San Francisco, CA",
        "price": 2867,
        "link": "https://www.zillow.com//b/alta-potrero-san-francisco-ca-9tWYvF/"
    },
    "5": {
        "address": "Vara | 1600 15th St, San Francisco, CA",
        "price": 2838,
        "link": "https://www.zillow.com//b/vara-san-francisco-ca-5XrPmJ/"
    },
    "6": {
        "address": "33 8th at Trinity Place | 33 8th St, San Francisco, CA",
        "price": 2549,
        "link": "https://www.zillow.com//b/33-8th-at-trinity-place-san-francisco-ca-9NJw4S/"
    },
    "7": {
        "address": "AVA 55 Ninth | 55 9th St, San Francisco, CA",
        "price": 2640,
        "link": "https://www.zillow.com//b/ava-55-ninth-san-francisco-ca-5XkH8X/"
    },
    "8": {
        "address": "Prism | 1028 Market St, San Francisco, CA",
        "price": 2744,
        "link": "https://www.zillow.com//b/prism-san-francisco-ca-9NJpRh/"
    },
    "9": {
        "address": "Chorus, 30 Otis St #629, San Francisco, CA 94103",
        "price": 2961,
        "link": "https://www.zillow.com/https://www.zillow.com/b/chorus-san-francisco-ca-9NJvt7/"
    },
    "10": {
        "address": "1190 Mission at Trinity Place | 1190 Mission St, San Francisco, CA",
        "price": 2499,
        "link": "https://www.zillow.com//b/1190-mission-at-trinity-place-san-francisco-ca-5XjVtb/"
    },
    "11": {
        "address": "1188 Mission at Trinity Place | 1188 Mission St, San Francisco, CA",
        "price": 2649,
        "link": "https://www.zillow.com//b/1188-mission-at-trinity-place-san-francisco-ca-5XjN4q/"
    },
    "12": {
        "address": "Hanover Soma West, 1140 Harrison St #UO5, San Francisco, CA 94103",
        "price": 2976,
        "link": "https://www.zillow.com/https://www.zillow.com/b/hanover-soma-west-san-francisco-ca-9NJsx9/"
    },
    "13": {
        "address": "947 Bush | 947 Bush St, San Francisco, CA",
        "price": 2595,
        "link": "https://www.zillow.com//b/947-bush-san-francisco-ca-5XjW9S/"
    },
    "14": {
        "address": "AVA Nob Hill | 965 Sutter St, San Francisco, CA",
        "price": 2615,
        "link": "https://www.zillow.com//b/ava-nob-hill-san-francisco-ca-5XkHq6/"
    },
    "15": {
        "address": "Astella | 975 Bryant St, San Francisco, CA",
        "price": 2977,
        "link": "https://www.zillow.com//b/astella-san-francisco-ca-9NJxqH/"
    },
    "17": {
        "address": "1177 Market at Trinity Place | 1177 Market St, San Francisco, CA",
        "price": 2399,
        "link": "https://www.zillow.com//b/1177-market-at-trinity-place-san-francisco-ca-BNjvdD/"
    },
    "18": {
        "address": "Avalon at Mission Bay, 255 King St, San Francisco, CA 94107",
        "price": 2890,
        "link": "https://www.zillow.com/https://www.zillow.com/b/avalon-at-mission-bay-san-francisco-ca-5XjVCw/"
    },
    "19": {
        "address": "1333 Gough Apartments at Cathedral Hall | 1333 Gough St, San Francisco, CA",
        "price": 2950,
        "link": "https://www.zillow.com//b/1333-gough-apartments-at-cathedral-hall-san-francisco-ca-5XjRmn/"
    },
    "20": {
        "address": "Olume, 1401 Mission St #1104, San Francisco, CA 94103",
        "price": 2923,
        "link": "https://www.zillow.com/https://www.zillow.com/b/olume-san-francisco-ca-5Yy6VF/"
    },
    "21": {
        "address": "Mission Bay by Windsor, 360 Berry St APT 108, San Francisco, CA 94158",
        "price": 2720,
        "link": "https://www.zillow.com/https://www.zillow.com/b/mission-bay-by-windsor-san-francisco-ca-9NM9Sk/"
    },
    "22": {
        "address": "990 Geary | 990 Geary St, San Francisco, CA",
        "price": 2895,
        "link": "https://www.zillow.com//b/990-geary-san-francisco-ca-5XjSTc/"
    },
    "23": {
        "address": "The Landing | 1395 22nd St, San Francisco, CA",
        "price": 2613,
        "link": "https://www.zillow.com//b/the-landing-san-francisco-ca-9NK3gC/"
    },
    "24": {
        "address": "2440 Van Ness Ave, 2440 Van Ness Ave, San Francisco, CA 94109",
        "price": 2595,
        "link": "https://www.zillow.com/https://www.zillow.com/b/2440-van-ness-ave-san-francisco-ca-9NKHF3/"
    },
    "25": {
        "address": "The Presidio Landmark, 1801 Wedemeyer St #119, San Francisco, CA 94129",
        "price": 2890,
        "link": "https://www.zillow.com/https://www.zillow.com/b/the-presidio-landmark-san-francisco-ca-5XkJwH/"
    },
    "26": {
        "address": "Vance, 830 Eddy St #603, San Francisco, CA 94109",
        "price": 2780,
        "link": "https://www.zillow.com/https://www.zillow.com/b/vance-san-francisco-ca-9NKJBx/"
    },
    "27": {
        "address": "Trinity Towers Apartments | 888 Ofarrell St, San Francisco, CA",
        "price": 2099,
        "link": "https://www.zillow.com//b/trinity-towers-apartments-san-francisco-ca-5XjPdR/"
    },
    "28": {
        "address": "The Wilson | 973 Market St, San Francisco, CA",
        "price": 2333,
        "link": "https://www.zillow.com//b/the-wilson-san-francisco-ca-5gKCZ8/"
    },
    "29": {
        "address": "50 Jones | 50 Jones St, San Francisco, CA",
        "price": 2456,
        "link": "https://www.zillow.com//b/50-jones-san-francisco-ca-Bntcg2/"
    },
    "30": {
        "address": "Mt. Sutro | 480 Warren Dr, San Francisco, CA",
        "price": 2495,
        "link": "https://www.zillow.com//b/mt.-sutro-san-francisco-ca-5XjVRC/"
    },
    "31": {
        "address": "480 Potrero Ave, 480 Potrero Ave #404, San Francisco, CA 94110",
        "price": 2900,
        "link": "https://www.zillow.com/https://www.zillow.com/b/480-potrero-ave-san-francisco-ca-5mY4JQ/"
    },
    "32": {
        "address": "845 Sutter, 845 Sutter St APT 409, San Francisco, CA 94109",
        "price": 2350,
        "link": "https://www.zillow.com/https://www.zillow.com/b/845-sutter-san-francisco-ca-5XkKMm/"
    },
    "33": {
        "address": "140 Haight | 140 Haight St, San Francisco, CA",
        "price": 2895,
        "link": "https://www.zillow.com//b/140-haight-san-francisco-ca-5ZpQXT/"
    },
    "34": {
        "address": "NorthPoint Apartments, 2211 Stockton St, San Francisco, CA 94133",
        "price": 2810,
        "link": "https://www.zillow.com/https://www.zillow.com/b/northpoint-apartments-san-francisco-ca-5XjLPJ/"
    },
    "35": {
        "address": "275 Turk St, 275 Turk St #512, San Francisco, CA 94102",
        "price": 2395,
        "link": "https://www.zillow.com/https://www.zillow.com/b/275-turk-st-san-francisco-ca-5Xmfjr/"
    },
    "36": {
        "address": "Geary Courtyard, 639 Geary St #1-214, San Francisco, CA 94102",
        "price": 2504,
        "link": "https://www.zillow.com/https://www.zillow.com/b/geary-courtyard-san-francisco-ca-5XjRSd/"
    },
    "37": {
        "address": "2133 Stockton Street Apartments | 2133 Stockton St, San Francisco, CA",
        "price": 2499,
        "link": "https://www.zillow.com//b/2133-stockton-street-apartments-san-francisco-ca-5Xhzkj/"
    },
    "38": {
        "address": "The Martin, 2051 3rd St APT 111, San Francisco, CA 94107",
        "price": 2949,
        "link": "https://www.zillow.com/https://www.zillow.com/b/the-martin-san-francisco-ca-9NK4bh/"
    },
    "39": {
        "address": "Edgewater | 355 Berry St, San Francisco, CA",
        "price": 2604,
        "link": "https://www.zillow.com//b/edgewater-san-francisco-ca-5XjVQc/"
    },
    "40": {
        "address": "333 Fremont, 333 Fremont St APT 107, San Francisco, CA 94105",
        "price": 2972,
        "link": "https://www.zillow.com/https://www.zillow.com/b/333-fremont-san-francisco-ca-5gjwKL/"
    },
    "41": {
        "address": "NorthPoint Vistas, 2351 Powell St, San Francisco, CA 94133",
        "price": 3000,
        "link": "https://www.zillow.com/https://www.zillow.com/b/northpoint-vistas-san-francisco-ca-5XqJsJ/"
    }
}